setup.py
xmlobject/__init__.py
xmlobject/xmlobject.py
xmlobject.egg-info/PKG-INFO
xmlobject.egg-info/SOURCES.txt
xmlobject.egg-info/dependency_links.txt
xmlobject.egg-info/top_level.txt