Metadata-Version: 1.0
Name: xmlobject
Version: 0.1
Summary: Interface XML using neat Python syntax
Home-page: UNKNOWN
Author: Tobias Mueller
Author-email: tobiasmue@gnome.org
License: GNU GPL v3+
Platform: Any
Classifier: Development Status :: 4 - Beta
Classifier: Environment :: Console
Classifier: Intended Audience :: Developers
Classifier: License :: OSI Approved :: GNU General Public License (GPL)
Classifier: Operating System :: OS Independent
Classifier: Topic :: Software Development :: Libraries :: Python Modules
Classifier: Topic :: Text Processing :: Markup :: XML
